chatgpt_hj3415/__init__.py
chatgpt_hj3415/gpt.py
chatgpt_hj3415/prompt/__init__.py
chatgpt_hj3415/prompt/by_nfs.py
chatgpt_hj3415/prompt/by_price.py
chatgpt_hj3415/prompt/intro.py
chatgpt_hj3415-0.4.1.dist-info/WHEEL
chatgpt_hj3415-0.4.1.dist-info/METADATA
chatgpt_hj3415-0.4.1.dist-info/RECORD
