Metadata-Version: 2.4
Name: chatgpt_hj3415
Version: 0.4.1
Summary: chatgpt-hj3415 is the program using chatgpt api.
Author-email: Hyungjin Kim <hj3415@gmail.com>
Classifier: License :: OSI Approved :: MIT License
Requires-Dist: openai
Requires-Dist: pandas
Requires-Dist: utils_hj3415
Requires-Dist: db2_hj3415
Project-URL: Home, https://www.hyungjin.kr
